django_graph_auth-0.3.1.dist-info/DESCRIPTION.rst
django_graph_auth-0.3.1.dist-info/METADATA
django_graph_auth-0.3.1.dist-info/RECORD
django_graph_auth-0.3.1.dist-info/WHEEL
django_graph_auth-0.3.1.dist-info/metadata.json
django_graph_auth-0.3.1.dist-info/top_level.txt
graph_auth/__init__.py
graph_auth/apps.py
graph_auth/schema.py
graph_auth/settings.py
